jaxgeometry/__init__.py
jaxgeometry/params.py
jaxgeometry/plotting.py
jaxgeometry/setup.py
jaxgeometry/utils.py
jaxgeometry/Riemannian/Log.py
jaxgeometry/Riemannian/__init__.py
jaxgeometry/Riemannian/curvature.py
jaxgeometry/Riemannian/geodesic.py
jaxgeometry/Riemannian/metric.py
jaxgeometry/Riemannian/parallel_transport.py
jaxgeometry/dynamics/Hamiltonian.py
jaxgeometry/dynamics/MPP_Kunita.py
jaxgeometry/dynamics/MPP_Kunita_Log.py
jaxgeometry/dynamics/MPP_group.py
jaxgeometry/dynamics/MPP_landmarks.py
jaxgeometry/dynamics/MPP_landmarks_Log.py
jaxgeometry/dynamics/flow.py
jaxgeometry/dynamics/flow_differential.py
jaxgeometry/framebundle/FM.py
jaxgeometry/framebundle/MPP.py
jaxgeometry/group/EulerPoincare.py
jaxgeometry/group/LiePoisson.py
jaxgeometry/group/energy.py
jaxgeometry/group/invariant_metric.py
jaxgeometry/group/quotient.py
jaxgeometry/groups/GLN.py
jaxgeometry/groups/SON.py
jaxgeometry/groups/__init__.py
jaxgeometry/groups/group.py
jaxgeometry/manifolds/Euclidean.py
jaxgeometry/manifolds/H2.py
jaxgeometry/manifolds/Heisenberg.py
jaxgeometry/manifolds/S2.py
jaxgeometry/manifolds/SPDN.py
jaxgeometry/manifolds/cylinder.py
jaxgeometry/manifolds/ellipsoid.py
jaxgeometry/manifolds/landmarks.py
jaxgeometry/manifolds/latent.py
jaxgeometry/manifolds/manifold.py
jaxgeometry/manifolds/torus.py
jaxgeometry/sR/__init__.py
jaxgeometry/sR/metric.py
jaxgeometry/statistics/Frechet_mean.py
jaxgeometry/statistics/diffusion_mean.py
jaxgeometry/statistics/iterative_mle.py
jaxgeometry/statistics/tangent_PCA.py
jaxgeometry/stochastics/Brownian_coords.py
jaxgeometry/stochastics/Brownian_development.py
jaxgeometry/stochastics/Brownian_inv.py
jaxgeometry/stochastics/Brownian_process.py
jaxgeometry/stochastics/Brownian_sR.py
jaxgeometry/stochastics/Eulerian.py
jaxgeometry/stochastics/Langevin.py
jaxgeometry/stochastics/__init__.py
jaxgeometry/stochastics/diagonal_conditioning.py
jaxgeometry/stochastics/guided_process.py
jaxgeometry/stochastics/product_sde.py
jaxdifferentialgeometry-0.9.4.dist-info/LICENSE
jaxdifferentialgeometry-0.9.4.dist-info/METADATA
jaxdifferentialgeometry-0.9.4.dist-info/WHEEL
jaxdifferentialgeometry-0.9.4.dist-info/top_level.txt
jaxdifferentialgeometry-0.9.4.dist-info/RECORD
