Metadata-Version: 2.1
Name: jaxdifferentialgeometry
Version: 0.9.4
Summary: Differential geometry using jax
Author-email: Stefan Sommer <sommer@di.ku.dk>
Project-URL: Homepage, https://bitbucket.org/stefansommer/jaxgeometry/
Project-URL: Issues, https://bitbucket.org/stefansommer/jaxgeometry/issues
Classifier: Programming Language :: Python :: 3
Classifier: License :: OSI Approved :: GNU General Public License v3 (GPLv3)
Classifier: Operating System :: OS Independent
Requires-Python: >=3.8
License-File: LICENSE
Requires-Dist: jax
Requires-Dist: jaxlib
Requires-Dist: jupyter
Requires-Dist: matplotlib
Requires-Dist: scikit-learn
